cloud_map/__init__.py
cloud_map/discovery/__init__.py
cloud_map/discovery/aws_compute_discoverer.py
cloud_map/discovery/aws_database_discoverer.py
cloud_map/discovery/aws_network_discoverer.py
cloud_map/discovery/aws_network_utilities_discoverer.py
cloud_map/discovery/aws_serverless_discoverer.py
cloud_map/discovery/boto3_caller.py
cloud_map/discovery/interfaces.py
cloud_map/executor/__init__.py
cloud_map/executor/cloud_map_executor.py
cloud_map/executor/main.py
cloud_map/executor/organizer.py
cloud_map/executor/output_manager.py
cloud_map/model/__init__.py
cloud_map/model/enums.py
cloud_map/model/models.py
cloud_map/presentation/__init__.py
cloud_map/presentation/diagram.py
cloud_map/presentation/interfaces.py
cloud_map/presentation/plantuml_generator.py
cloud_map_py-0.1.4.dist-info/METADATA
cloud_map_py-0.1.4.dist-info/WHEEL
cloud_map_py-0.1.4.dist-info/entry_points.txt
cloud_map_py-0.1.4.dist-info/licenses/LICENSE
cloud_map_py-0.1.4.dist-info/RECORD
