Metadata-Version: 2.4
Name: cloud-map-py
Version: 0.1.4
Summary: AWS Cloud Infrastructure Mapper - Visualize and analyze AWS cloud resources
Author-email: Your Name <your.email@example.com>
Maintainer-email: Your Name <your.email@example.com>
License: MIT
License-File: LICENSE
Keywords: aws,cloud,infrastructure,mapping,plantuml,visualization
Classifier: Development Status :: 3 - Alpha
Classifier: Intended Audience :: Developers
Classifier: Intended Audience :: System Administrators
Classifier: License :: OSI Approved :: MIT License
Classifier: Operating System :: OS Independent
Classifier: Programming Language :: Python :: 3
Classifier: Programming Language :: Python :: 3.12
Classifier: Topic :: Software Development :: Libraries :: Python Modules
Classifier: Topic :: System :: Systems Administration
Requires-Python: >=3.12
Requires-Dist: boto3>=1.34.0
Requires-Dist: botocore>=1.34.0
Provides-Extra: dev
Requires-Dist: boto3-stubs[apigateway,ec2,lambda,route53]>=1.39.14; extra == 'dev'
Requires-Dist: mypy>=1.17.0; extra == 'dev'
Requires-Dist: types-boto3>=1.39.14; extra == 'dev'
Provides-Extra: plantuml
Requires-Dist: plantuml>=0.3.0; extra == 'plantuml'
